{"phases": [], "container": {"node_guid": null, "in_case": false, "sensitivity": "amber", "create_time": "2019-09-20T06:31:08.307845Z", "tenant_id": 0, "role_id": null, "id": 68, "custom_fields": {"action id": "update_event"}, "asset_id": null, "close_time": "2019-10-08T16:42:19.365502Z", "open_time": null, "status_id": 3, "container_type": "default", "closing_owner_id": 1, "current_phase_id": null, "due_time": "2019-09-20T18:30:51.187000Z", "version": 1, "workflow_name": "", "owner_id": 1, "status": "closed", "owner_name": null, "hash": "0d50f905648d6d825a1029c6d11002f3", "description": "update_event", "tags": [], "start_time": "2019-09-20T06:31:08.319030Z", "severity_id": "medium", "kill_chain": null, "artifact_update_time": "2019-09-20T06:34:56.558216Z", "artifact_count": 1, "parent_container_id": null, "data": {}, "name": "Splunk Enterprise Demo", "ingest_app_id": null, "label": "demo_configuration", "source_data_identifier": "8de9f04d-cd44-4464-a192-465c68a0e9ca", "end_time": null, "closing_rule_run_id": null, "container_update_time": "2019-10-08T16:44:30.257730Z"}, "attachments": [{"user_id": 1, "name": "splunk-update-rare_process.json", "task_id": null, "container_id": 68, "vault_document_id": 45, "create_time": "2019-09-20T06:33:44.118469Z", "id": 45}, {"user_id": 1, "name": "update_event_rare_process_replacerizer.json", "task_id": null, "container_id": 68, "vault_document_id": 44, "create_time": "2019-09-20T06:33:43.785492Z", "id": 44}], "artifacts": [{"in_case": false, "create_time": "2019-09-20T06:34:24.467995Z", "id": 420, "parent_artifact_id": null, "label": "event", "version": 1, "has_note": false, "type": null, "owner_id": 1, "cef": {"dummy_default": "True", "replacerizer": "07851919cd6fdd8b66d2cd315c4532b091b1b727", "dummy_file_vault_id": "089cdfaada8809b4ebe71da435b240ade939697c"}, "update_time": "2019-09-20T06:34:56.548726Z", "hash": "e04f22327568e9bfb087ff20bba3b61d", "description": null, "tags": [], "cef_types": {}, "start_time": "2019-09-20T06:34:24.472825Z", "container_id": 68, "severity_id": "medium", "kill_chain": null, "playbook_run_id": null, "parent_container_id": null, "data": {}, "name": "matching criteria", "ingest_app_id": null, "source_data_identifier": "cfa11325-1dad-4142-9e3f-6c048914b23a", "end_time": null}], "vault_documents": [{"first_seen_time": "2019-09-20T06:33:43.791120Z", "hash": "07851919cd6fdd8b66d2cd315c4532b091b1b727", "version": 1, "tags": [], "deleted": false, "contains": ["vault id"], "sources": [{"user_id": 1}], "meta": {"size": 108, "sha256": "3fe5c068ae36c0021851da251785133ecd619f41899497fc17ce52e6fc40a95f", "contains": ["vault id"], "sha1": "07851919cd6fdd8b66d2cd315c4532b091b1b727", "md5": "aa7fb24af2c612ad77cd8e72b2844b9c"}, "names": ["update_event_rare_process_replacerizer.json"], "id": 44, "size": 108}, {"first_seen_time": "2019-09-20T06:33:44.124405Z", "hash": "089cdfaada8809b4ebe71da435b240ade939697c", "version": 1, "tags": [], "deleted": false, "contains": ["vault id"], "sources": [{"user_id": 1}], "meta": {"size": 1146, "sha256": "7e972ad6a4574ceb5c8f409199fccfeb0fdbf2972bc2db227292ef97c9e522c9", "contains": ["vault id"], "sha1": "089cdfaada8809b4ebe71da435b240ade939697c", "md5": "cf67e1d92ac37c78dbaa9c643a7f08d0"}, "names": ["splunk-update-rare_process.json"], "id": 45, "size": 1146}], "notes": [], "comments": [], "evidence": []}