{"phases": [], "container": {"node_guid": null, "in_case": false, "sensitivity": "amber", "create_time": "2019-09-13T06:02:58.235075Z", "tenant_id": 0, "role_id": null, "id": 51, "custom_fields": {"action id": "unblock hash 6d390038003c298c7ab8f2cbe35a50b07e096554", "Auto_Response_Received": ""}, "asset_id": null, "close_time": "2019-10-08T16:42:17.352884Z", "open_time": null, "status_id": 3, "container_type": "default", "closing_owner_id": 1, "current_phase_id": null, "due_time": "2019-09-13T18:02:47.951000Z", "version": 1, "workflow_name": "", "owner_id": 1, "status": "closed", "owner_name": "admin", "hash": "6084f703b9477b42c1c8000918849ad0", "description": "unblock_hash", "tags": [], "start_time": "2019-09-13T06:02:58.256302Z", "severity_id": "medium", "kill_chain": null, "artifact_update_time": "2019-09-13T06:04:40.621700Z", "artifact_count": 1, "parent_container_id": null, "data": {}, "name": "Carbon Black Response Demo", "ingest_app_id": null, "label": "demo_configuration", "source_data_identifier": "c1424f0a-c7cb-4463-af54-21376203758f", "end_time": null, "closing_rule_run_id": null, "container_update_time": "2019-10-08T16:44:31.523456Z"}, "attachments": [{"user_id": 1, "name": "rareprocess-hash-replacerizer.json", "task_id": null, "container_id": 51, "vault_document_id": 15, "create_time": "2019-09-13T06:03:21.484830Z", "id": 16}, {"user_id": 1, "name": "carbon-black-response-unblock-hash.json", "task_id": null, "container_id": 51, "vault_document_id": 16, "create_time": "2019-09-13T06:03:21.717330Z", "id": 15}], "artifacts": [{"in_case": false, "create_time": "2019-09-13T06:04:23.728339Z", "id": 401, "parent_artifact_id": null, "label": "event", "version": 1, "has_note": false, "type": null, "owner_id": 1, "cef": {"hash": "6d390038003c298c7ab8f2cbe35a50b07e096554", "replacerizer": "fe8cf2851660359df7892dabad048cc9bd923d1f", "dummy_file_vault_id": "7719a111aee747db39a164ded7de55bccbf2e98c"}, "update_time": "2019-09-13T06:04:40.604934Z", "hash": "385a08d7905d1441fd892fe933faaacb", "description": null, "tags": [], "cef_types": {}, "start_time": "2019-09-13T06:04:23.737676Z", "container_id": 51, "severity_id": "medium", "kill_chain": null, "playbook_run_id": null, "parent_container_id": null, "data": {}, "name": "matching criteria", "ingest_app_id": null, "source_data_identifier": "eb5187b3-392c-4b1b-a61d-c30ed84df103", "end_time": null}], "vault_documents": [{"first_seen_time": "2019-09-13T04:55:51.925007Z", "hash": "fe8cf2851660359df7892dabad048cc9bd923d1f", "version": 1, "tags": [], "deleted": false, "contains": ["vault id"], "sources": [{"user_id": 3}, {"user_id": 3}, {"user_id": 3}, {"user_id": 3}, {"user_id": 3}], "meta": {"size": 86, "sha256": "f1ee261a616a2c6aa44c1b749d5be872101a0b799a96276daebc1717407e200c", "contains": ["vault id"], "sha1": "fe8cf2851660359df7892dabad048cc9bd923d1f", "md5": "4d0db49a6e2eeead864b5be399284357"}, "names": ["hunt-file-replacerizer.json", "rareprocess-hash-replacerizer.json"], "id": 15, "size": 86}, {"first_seen_time": "2019-09-13T06:03:21.735243Z", "hash": "7719a111aee747db39a164ded7de55bccbf2e98c", "version": 1, "tags": [], "deleted": false, "contains": ["vault id"], "sources": [{"user_id": 3}], "meta": {"size": 313, "sha256": "a7bf21cbfcdb943331bf9939b81403194cfc77eb66dabf62aebe717976110219", "contains": ["vault id"], "sha1": "7719a111aee747db39a164ded7de55bccbf2e98c", "md5": "7dbff06a645d5012be6f810de16b3aec"}, "names": ["carbon-black-response-unblock-hash.json"], "id": 16, "size": 313}], "notes": [], "comments": [], "evidence": []}